parallel/__init__.py
parallel/parallelppdev.py
parallel/parallelutil.py
parallel/parallelwin32.py
pyparallel-0.2.2.dist-info/DESCRIPTION.rst
pyparallel-0.2.2.dist-info/METADATA
pyparallel-0.2.2.dist-info/RECORD
pyparallel-0.2.2.dist-info/WHEEL
pyparallel-0.2.2.dist-info/metadata.json
pyparallel-0.2.2.dist-info/top_level.txt
