Metadata-Version: 1.1
Name: pyparallel
Version: 0.2.2
Summary: Python Parallel Port Extension
Home-page: https://github.com/pyserial/pyparallel
Author: Chris Liechti
Author-email: cliechti@gmx.net
License: BSD
Platform: UNKNOWN
Classifier: Development Status :: 4 - Beta
Classifier: Intended Audience :: Developers
Classifier: License :: OSI Approved :: BSD License
Classifier: Natural Language :: English
Classifier: Operating System :: POSIX
Classifier: Operating System :: Microsoft :: Windows
Classifier: Programming Language :: Python
Classifier: Programming Language :: Python :: 3
Classifier: Topic :: Communications
Classifier: Topic :: Software Development :: Libraries
